ovos_color_parser/__init__.py
ovos_color_parser/matching.py
ovos_color_parser/models.py
ovos_color_parser/version.py
ovos_color_parser/res/webcolors.json
ovos_color_parser/res/ca/colors.json
ovos_color_parser/res/cs/colors.json
ovos_color_parser/res/da/99colors.json
ovos_color_parser/res/da/ISCC-NBS.json
ovos_color_parser/res/da/RAL_classic.json
ovos_color_parser/res/da/RAL_design.json
ovos_color_parser/res/da/RAL_effect.json
ovos_color_parser/res/da/RAL_plastics_p1.json
ovos_color_parser/res/da/RAL_plastics_p2.json
ovos_color_parser/res/da/color_descriptors.json
ovos_color_parser/res/da/colors.json
ovos_color_parser/res/da/crayola.json
ovos_color_parser/res/da/dot-net-colors.json
ovos_color_parser/res/da/japan_colors.json
ovos_color_parser/res/da/object_colors.json
ovos_color_parser/res/da/pantome_colors.json
ovos_color_parser/res/da/wikipedia_color_list.json
ovos_color_parser/res/da/xkcd_colors.json
ovos_color_parser/res/de/99colors.json
ovos_color_parser/res/de/color_descriptors.json
ovos_color_parser/res/de/colors.json
ovos_color_parser/res/de/wikipedia_color_list.json
ovos_color_parser/res/en/99colors.json
ovos_color_parser/res/en/ISCC-NBS.json
ovos_color_parser/res/en/RAL_classic.json
ovos_color_parser/res/en/RAL_design.json
ovos_color_parser/res/en/RAL_effect.json
ovos_color_parser/res/en/RAL_plastics_p1.json
ovos_color_parser/res/en/RAL_plastics_p2.json
ovos_color_parser/res/en/color_descriptors.json
ovos_color_parser/res/en/colors.json
ovos_color_parser/res/en/crayola.json
ovos_color_parser/res/en/dot-net-colors.json
ovos_color_parser/res/en/japan_colors.json
ovos_color_parser/res/en/object_colors.json
ovos_color_parser/res/en/pantome_colors.json
ovos_color_parser/res/en/wikipedia_color_list.json
ovos_color_parser/res/en/xkcd_colors.json
ovos_color_parser/res/es/99colors.json
ovos_color_parser/res/es/color_descriptors.json
ovos_color_parser/res/es/colors.json
ovos_color_parser/res/es/wikipedia_color_list.json
ovos_color_parser/res/eu/99colors.json
ovos_color_parser-0.0.8.dist-info/METADATA
ovos_color_parser-0.0.8.dist-info/WHEEL
ovos_color_parser-0.0.8.dist-info/top_level.txt
ovos_color_parser-0.0.8.dist-info/RECORD
