Metadata-Version: 2.1
Name: ovos-color-parser
Version: 0.0.8
Summary: OpenVoiceOS's multilingual text color parsing and formatting library
Home-page: https://github.com/OpenVoiceOS/ovos-color-parser
Author: Mycroft AI / OVOS
Author-email: jarbasai@mailfence.com
License: Apache2.0
Classifier: Development Status :: 4 - Beta
Classifier: Intended Audience :: Developers
Classifier: Topic :: Text Processing :: Linguistic
Classifier: License :: OSI Approved :: Apache Software License
Classifier: Programming Language :: Python :: 3.6
Classifier: Programming Language :: Python :: 3.7
Classifier: Programming Language :: Python :: 3.8
Classifier: Programming Language :: Python :: 3.9
Requires-Dist: colorspacious
Requires-Dist: pyahocorasick
